mutalyzer_api/__init__.py
mutalyzer_api/api.py
mutalyzer_api/endpoints/__init__.py
mutalyzer_api/endpoints/api.py
mutalyzer_api/endpoints/back_translate.py
mutalyzer_api/endpoints/common.py
mutalyzer_api/endpoints/compare.py
mutalyzer_api/endpoints/delins_model.py
mutalyzer_api/endpoints/description_extract.py
mutalyzer_api/endpoints/description_to_model.py
mutalyzer_api/endpoints/get_selectors.py
mutalyzer_api/endpoints/map.py
mutalyzer_api/endpoints/mutate.py
mutalyzer_api/endpoints/normalize.py
mutalyzer_api/endpoints/position_convert.py
mutalyzer_api/endpoints/reference_model.py
mutalyzer_api/endpoints/related_references.py
mutalyzer_api/endpoints/spdi_converter.py
mutalyzer_api/endpoints/view_variants.py
mutalyzer_api-0.3.2.dist-info/licenses/LICENSE
mutalyzer_api-0.3.2.dist-info/METADATA
mutalyzer_api-0.3.2.dist-info/WHEEL
mutalyzer_api-0.3.2.dist-info/entry_points.txt
mutalyzer_api-0.3.2.dist-info/top_level.txt
mutalyzer_api-0.3.2.dist-info/RECORD
