Metadata-Version: 2.4
Name: mutalyzer_api
Version: 0.3.2
Summary: Mutalyzer HGVS variant description normalizer.
Home-page: https://github.com/mutalyzer/api
Author: Mihai Lefter
Author-email: M.Lefter@lumc.nl
License: MIT
Keywords: Mutalyzer,HGVS
Classifier: Intended Audience :: Science/Research
Classifier: Intended Audience :: Developers
Classifier: Operating System :: OS Independent
Classifier: Programming Language :: Python :: 3
Classifier: Topic :: Scientific/Engineering :: Bio-Informatics
License-File: LICENSE
Requires-Dist: mutalyzer>=3.1.0
Requires-Dist: flask-restx>=1.3.0
Requires-Dist: Flask-Cors>=4.0.0
Dynamic: license-file
